Metadata-Version: 2.2
Name: adam_community
Version: 1.0.28
Summary: Adam Community Tools and Utilities
Home-page: https://github.com/yourusername/adam-community
Author: Adam Community
Author-email: admin@sidereus-ai.com
Classifier: Programming Language :: Python :: 3
Classifier: License :: OSI Approved :: MIT License
Classifier: Operating System :: OS Independent
Requires-Python: >=3.8
Requires-Dist: requests>=2.31.0
Requires-Dist: click>=8.0.0
Requires-Dist: docstring-parser>=0.15
Requires-Dist: rich>=13.0.0
Requires-Dist: packaging>=21.0
Requires-Dist: jsonschema>=4.0.0
Requires-Dist: jinja2>=3.0.0
Requires-Dist: prompt-toolkit
Dynamic: author
Dynamic: author-email
Dynamic: classifier
Dynamic: description
Dynamic: description-content-type
Dynamic: home-page
Dynamic: requires-dist
Dynamic: requires-python
Dynamic: summary
